datura_api/__init__.py
datura_api/datura_api_sdk.py
datura_api/protocol.py
datura_api-0.0.10.dist-info/METADATA
datura_api-0.0.10.dist-info/WHEEL
datura_api-0.0.10.dist-info/top_level.txt
datura_api-0.0.10.dist-info/RECORD
